jsonstar/__init__.py
jsonstar/decoder.py
jsonstar/default_encoders.py
jsonstar/encoder.py
jsonstar/null_dict.py
jsonstar-1.1.1.dist-info/LICENSE
jsonstar-1.1.1.dist-info/METADATA
jsonstar-1.1.1.dist-info/WHEEL
jsonstar-1.1.1.dist-info/RECORD
