Metadata-Version: 2.3
Name: jsonstar
Version: 1.1.1
Summary: Extensible JSON module to serialize all objects.
License: MIT
Author: Henrique Bastos
Author-email: henrique@bastos.net
Requires-Python: >=3.9
Classifier: Development Status :: 5 - Production/Stable
Classifier: Intended Audience :: Developers
Classifier: License :: OSI Approved :: MIT License
Classifier: Operating System :: OS Independent
Classifier: Programming Language :: Python :: 3
Classifier: Programming Language :: Python :: 3.9
Classifier: Programming Language :: Python :: 3.10
Classifier: Programming Language :: Python :: 3.11
Classifier: Programming Language :: Python :: 3.12
Classifier: Programming Language :: Python :: 3.13
Classifier: Programming Language :: Python :: 3.8
Classifier: Programming Language :: Python :: Implementation :: CPython
Classifier: Programming Language :: Python :: Implementation :: PyPy
Classifier: Topic :: Software Development :: Libraries :: Python Modules
Project-URL: Documentation, https://github.com/henriquebastos/python-jsonstar
Project-URL: Homepage, https://github.com/henriquebastos/python-jsonstar
Project-URL: Issues, https://github.com/henriquebastos/python-jsonstar/issues
Project-URL: Repository, https://github.com/henriquebastos/python-jsonstar
